README.rst
setup.cfg
setup.py
revrand/__init__.py
revrand/basis_functions.py
revrand/btypes.py
revrand/glm.py
revrand/likelihoods.py
revrand/metrics.py
revrand/slm.py
revrand.egg-info/PKG-INFO
revrand.egg-info/SOURCES.txt
revrand.egg-info/dependency_links.txt
revrand.egg-info/requires.txt
revrand.egg-info/top_level.txt
revrand/mathfun/__init__.py
revrand/mathfun/linalg.py
revrand/mathfun/special.py
revrand/optimize/__init__.py
revrand/optimize/decorators.py
revrand/optimize/sgd.py
revrand/utils/__init__.py
revrand/utils/base.py
revrand/utils/datasets.py
revrand/utils/decorators.py
revrand/utils/rand.py